GitCommitChart/__init__.py
pygitcontributionchart-0.0.3.dist-info/METADATA
pygitcontributionchart-0.0.3.dist-info/WHEEL
pygitcontributionchart-0.0.3.dist-info/top_level.txt
pygitcontributionchart-0.0.3.dist-info/RECORD
