Metadata-Version: 2.4
Name: PyGitContributionChart
Version: 0.0.3
Summary: A package for generating Git contribution charts
Home-page: https://github.com/arkangel-dev/GitCommitChart
Author: Sam Ramirez
Classifier: Programming Language :: Python :: 3
Requires-Python: >=3.6
Requires-Dist: pillow==10.2.0
Dynamic: author
Dynamic: classifier
Dynamic: description
Dynamic: description-content-type
Dynamic: home-page
Dynamic: requires-dist
Dynamic: requires-python
Dynamic: summary
